pyuefi/__init__.py
pyuefi/update_mbr_ptypes.py
pyuefi/pyuefi.py
pyuefi/Forensie.py
pyuefi/partition_types/mbr.py
pyuefi/partition_types/__init__.py
pyuefi/partition_types/uefi.py
pyuefi-0.1.dist-info/top_level.txt
pyuefi-0.1.dist-info/DESCRIPTION.rst
pyuefi-0.1.dist-info/METADATA
pyuefi-0.1.dist-info/WHEEL
pyuefi-0.1.dist-info/RECORD
pyuefi-0.1.dist-info/metadata.json
